datetime_libs/__init__.py
datetime_libs/client_timezone.py
datetime_libs/datetime_libs.py
datetime_libs-1.1.dist-info/LICENSE
datetime_libs-1.1.dist-info/METADATA
datetime_libs-1.1.dist-info/WHEEL
datetime_libs-1.1.dist-info/top_level.txt
datetime_libs-1.1.dist-info/RECORD
